<?xml version="1.0" encoding="utf-8"?>
<ArrayOfEnginieer>
  <Engineer>
    <Id>306645777</Id>
    <Name>Moriya Atar</Name>
    <Email>MoriyaAtar@gmail.com</Email>
    <CostPerHour>331</CostPerHour>
    <EngineerLevel>Expert</EngineerLevel>
  </Engineer>
  <Engineer>
    <Id>352391129</Id>
    <Name>Tehila Chen</Name>
    <Email>TehilaChen@gmail.com</Email>
    <CostPerHour>410</CostPerHour>
    <EngineerLevel>Advanced</EngineerLevel>
  </Engineer>
  <Engineer>
    <Id>259200698</Id>
    <Name>Ortal Oren</Name>
    <Email>OrtalOren@gmail.com</Email>
    <CostPerHour>346</CostPerHour>
    <EngineerLevel>Advanced</EngineerLevel>
  </Engineer>
  <Engineer>
    <Id>200038498</Id>
    <Name>Lea Ashori</Name>
    <Email>LeaAshori@gmail.com</Email>
    <CostPerHour>205</CostPerHour>
    <EngineerLevel>AdvancedBeginner</EngineerLevel>
  </Engineer>
  <Engineer>
    <Id>279298810</Id>
    <Name>Moshe Lavi</Name>
    <Email>MosheLavi@gmail.com</Email>
    <CostPerHour>307</CostPerHour>
    <EngineerLevel>Beginner</EngineerLevel>
  </Engineer>
  <Engineer>
    <Id>111</Id>
    <Name>Tal</Name>
    <Email>t@gmail.com</Email>
    <CostPerHour>45</CostPerHour>
    <EngineerLevel>Expert</EngineerLevel>
  </Engineer>
</ArrayOfEnginieer>